calculator_cli/__init__.py
calculator_cli/calculator.py
calculator_cli/cli.py
calculator_with_cli-0.1.2.dist-info/METADATA
calculator_with_cli-0.1.2.dist-info/WHEEL
calculator_with_cli-0.1.2.dist-info/entry_points.txt
calculator_with_cli-0.1.2.dist-info/top_level.txt
calculator_with_cli-0.1.2.dist-info/RECORD
