Metadata-Version: 2.4
Name: Calculator_With_CLI
Version: 0.1.2
Summary: A simple calculator package with CLI support
Author: Ahmed
Author-email: ahmed.mca18@gmail.com
Classifier: Programming Language :: Python :: 3
Classifier: License :: OSI Approved :: MIT License
Classifier: Operating System :: OS Independent
Requires-Python: >=3.7
Dynamic: author
Dynamic: author-email
Dynamic: classifier
Dynamic: description
Dynamic: description-content-type
Dynamic: requires-python
Dynamic: summary
